searchads_api/__init__.py
searchads_api/api.py
apple_searchads_api-1.6.2.dist-info/LICENSE
apple_searchads_api-1.6.2.dist-info/METADATA
apple_searchads_api-1.6.2.dist-info/WHEEL
apple_searchads_api-1.6.2.dist-info/top_level.txt
apple_searchads_api-1.6.2.dist-info/RECORD
