Metadata-Version: 2.1
Name: apple-searchads-api
Version: 1.6.2
Summary: Apple SearchAds API non-official python library
Home-page: https://github.com/dapanas/searchads_api
Author: Abdul Majeed Alkattan
Author-email: alkattan@phiture.com
License: UNKNOWN
Keywords: python,searchads,library
Platform: UNKNOWN
License-File: LICENSE
Requires-Dist: requests (>=2.27.1)
Requires-Dist: PyJWT (==2.4.0)
Requires-Dist: cryptography (==3.4.8)
